<Instrument_State><State><Tuple Set="SENS:AVER" Value="Buffer Read at 2018-12-13T06:29:55.752000"/><Tuple Set="SENS:BAND" Value="Buffer Read at 2018-12-13T06:29:55.753000"/><Tuple Set="SOUR:POW" Value="Buffer Read at 2018-12-13T06:29:55.756000"/><Tuple Set="SENS:SWE:TYPE" Value="Buffer Read at 2018-12-13T06:29:55.754000"/><Tuple Set="SOUR:POW:CORR:STAT" Value="Buffer Read at 2018-12-13T06:29:55.757000"/><Tuple Set="SOUR:POW:SLOP" Value="Buffer Read at 2018-12-13T06:29:55.758000"/><Tuple Set="SENS:CORR:STAT" Value="Buffer Read at 2018-12-13T06:29:55.755000"/></State><State_Description><State_Timestamp>2018-12-13T06:29:55.761000</State_Timestamp><Instrument_Description>C:\ProgramData\Anaconda2\lib\site-packages\pyMez\Code\InstrumentControl\..\..\Instruments\E8361A_PNA_01.xml</Instrument_Description></State_Description></Instrument_State>